adeploy/__init__.py
adeploy/main.py
adeploy/common/__init__.py
adeploy/common/args.py
adeploy/common/colors.py
adeploy/common/deployment.py
adeploy/common/errors.py
adeploy/common/helpers.py
adeploy/common/kubectl.py
adeploy/common/logging.py
adeploy/common/provider.py
adeploy/common/version.py
adeploy/common/jinja/__init__.py
adeploy/common/jinja/dict.py
adeploy/common/jinja/env.py
adeploy/common/jinja/filters.py
adeploy/common/jinja/globals.py
adeploy/common/secrets/__init__.py
adeploy/common/secrets/docker_registry_secret.py
adeploy/common/secrets/generic_secret.py
adeploy/common/secrets/secret.py
adeploy/common/secrets/tls_secret.py
adeploy/common/secrets_provider/__init__.py
adeploy/common/secrets_provider/gopass_provider.py
adeploy/common/secrets_provider/plaintext_provider.py
adeploy/common/secrets_provider/provider.py
adeploy/common/secrets_provider/random_provider.py
adeploy/common/secrets_provider/shell_command_provider.py
adeploy/common/yaml/__init__.py
adeploy/common/yaml/find.py
adeploy/common/yaml/labels.py
adeploy/common/yaml/probes.py
adeploy/common/yaml/resources.py
adeploy/common/yaml/update.py
adeploy/providers/__init__.py
adeploy/providers/helm/README.md
adeploy/providers/helm/__init__.py
adeploy/providers/helm/deployer.py
adeploy/providers/helm/renderer.py
adeploy/providers/helm/tester.py
adeploy/providers/helm/watcher.py
adeploy/providers/helm/common/__init__.py
adeploy/providers/helm/common/helm.py
adeploy/providers/helm/common/helm_output.py
adeploy/providers/helm/common/helm_provider.py
adeploy/providers/jinja/README.md
adeploy/providers/jinja/__init__.py
adeploy/providers/jinja/deployer.py
adeploy/providers/jinja/renderer.py
adeploy/providers/jinja/tester.py
adeploy/providers/jinja/watcher.py
adeploy/steps/__init__.py
adeploy/steps/config.py
adeploy/steps/deploy.py
adeploy/steps/render.py
adeploy/steps/test.py
adeploy/steps/watch.py
adeploy-1.2.6.dist-info/licenses/LICENSE
adeploy-1.2.6.dist-info/METADATA
adeploy-1.2.6.dist-info/WHEEL
adeploy-1.2.6.dist-info/entry_points.txt
adeploy-1.2.6.dist-info/top_level.txt
adeploy-1.2.6.dist-info/RECORD
