Metadata-Version: 2.4
Name: adeploy
Version: 1.2.6
Summary: Universal deployment tool for Kubernetes that supports rendering and deployment of lightweight Jinja templated k8s manifests as well as complex Helm charts.
Author: awesome IT
Author-email: Daniel Morlock <daniel.morlock@awesome-it.de>, Daniel Bross <daniel.bross@awesome-it.de>, Robin Lutz <robin.lutz@awesome-it.de>, Adrian Vielsack <adrian.vielsack@awesome-it.de>, Philip Flohr <philip.flohr@awesome-it.de>
Project-URL: Homepage, https://awesome-it.de
Project-URL: Source, https://github.com/awesome-it/adeploy
Project-URL: Issues, https://github.com/awesome-it/adeploy/issues
Project-URL: Documentation, https://awesome-it.de/docs/adeploy/latest
Classifier: Programming Language :: Python :: 3
Classifier: License :: OSI Approved :: BSD License
Classifier: Operating System :: OS Independent
Requires-Python: >=3.8
License-File: LICENSE
Requires-Dist: colorama>=0.4.3
Requires-Dist: Jinja2~=3.1.6
Requires-Dist: PyYAML~=6.0.1
Requires-Dist: ruamel.yaml>=0.16.12
Requires-Dist: ruamel.yaml.clib>=0.2.2
Requires-Dist: packaging>=20.4
Requires-Dist: shortuuid>=1.0.1
Requires-Dist: watchdog>=3.0.0
Requires-Dist: jq==1.10.0
Dynamic: author
Dynamic: license-file
